aws_sso_magic/__init__.py
aws_sso_magic/__main__.py
aws_sso_magic/cli.py
aws_sso_magic/configure.py
aws_sso_magic/eks.py
aws_sso_magic/login.py
aws_sso_magic/logout.py
aws_sso_magic/utils.py
aws_sso_magic-1.0.36.dist-info/LICENSE
aws_sso_magic-1.0.36.dist-info/METADATA
aws_sso_magic-1.0.36.dist-info/WHEEL
aws_sso_magic-1.0.36.dist-info/entry_points.txt
aws_sso_magic-1.0.36.dist-info/RECORD
