Metadata-Version: 2.1
Name: aws-sso-magic
Version: 1.0.36
Summary: Magic credentials on the AWS CLI home using AWS SSO login
Home-page: https://github.com/javiortizmol/aws-sso-magic
License: Apache-2.0
Author: Javier Ortiz
Author-email: jahor2@gmail.com
Requires-Python: >=3.6,<4.0
Classifier: Development Status :: 4 - Beta
Classifier: Intended Audience :: Developers
Classifier: Intended Audience :: System Administrators
Classifier: License :: OSI Approved :: Apache Software License
Classifier: Operating System :: OS Independent
Classifier: Programming Language :: Python :: 3
Classifier: Programming Language :: Python :: 3.6
Classifier: Programming Language :: Python :: 3.7
Classifier: Programming Language :: Python :: 3.8
Classifier: Programming Language :: Python :: 3.9
Classifier: Programming Language :: Python :: 3.10
Classifier: Programming Language :: Python :: 3.11
Classifier: Topic :: Utilities
Requires-Dist: PyInquirer (>=1.0.3,<2.0.0)
Requires-Dist: aws-error-utils (>=1.0.4,<2.0.0)
Requires-Dist: aws-sso-lib (>=1.7.0,<2.0.0)
Requires-Dist: boto3 (>=1.17.20,<2.0.0)
Requires-Dist: click (>=7.1.2,<8.0.0)
Requires-Dist: jsonschema (>=3.2.0,<4.0.0)
Requires-Dist: python-dateutil (>=2.8.1,<3.0.0)
Requires-Dist: pyyaml (>=5.3.1,<6.0.0)
Project-URL: Repository, https://github.com/javiortizmol/aws-sso-magic
